package_calculator/Calculadora.py
package_calculator/__init__.py
package_calculator_zriiman84-0.0.2.dist-info/licenses/LICENSE
package_calculator_zriiman84-0.0.2.dist-info/METADATA
package_calculator_zriiman84-0.0.2.dist-info/WHEEL
package_calculator_zriiman84-0.0.2.dist-info/top_level.txt
package_calculator_zriiman84-0.0.2.dist-info/RECORD
