Metadata-Version: 2.4
Name: package_calculator_zriiman84
Version: 0.0.2
Summary: Un paquete que contiene una clase Calculadora para operaciones matemáticas básicas, con pyproject.toml
Author-email: Cristofer Vargas <crisric84@gmail.com>
License-Expression: MIT
Project-URL: Homepage, https://github.com/zriiman84/package_calculator
Classifier: Programming Language :: Python :: 3
Classifier: Operating System :: OS Independent
Requires-Python: >=3.10
License-File: LICENSE
Dynamic: license-file
